websites_metrics_consumer/__init__.py
websites_metrics_consumer/main.py
websites_metrics_consumer/classes/EventsHandler.py
websites_metrics_consumer/classes/__init__.py
websites_metrics_consumer/communication/__init__.py
websites_metrics_consumer/communication/consumers.py
websites_metrics_consumer/configuration/__init__.py
websites_metrics_consumer/configuration/init_db.py
websites_metrics_consumer/helpers/__init__.py
websites_metrics_consumer/helpers/confluent_kafka_configuration_builder.py
websites_metrics_consumer-0.0.3.dist-info/LICENSE
websites_metrics_consumer-0.0.3.dist-info/METADATA
websites_metrics_consumer-0.0.3.dist-info/WHEEL
websites_metrics_consumer-0.0.3.dist-info/top_level.txt
websites_metrics_consumer-0.0.3.dist-info/RECORD
