Metadata-Version: 2.1
Name: websites-metrics-consumer
Version: 0.0.3
Summary: An application that consumes metrics from Kafka messages and store the results into ta postgres db
Home-page: https://github.com/antoniodimariano/metrics_consumer
Author: Antonio Di Mariano
Author-email: antonio.dimariano@gmail.com
License: Apache 2.0
Platform: UNKNOWN
Classifier: Programming Language :: Python :: 3
Classifier: License :: OSI Approved :: Apache Software License
Classifier: Operating System :: OS Independent
Requires-Python: >=3.6
License-File: LICENSE
Requires-Dist: psycopg2
Requires-Dist: confluent-kafka
Requires-Dist: avro-python3
Requires-Dist: requests
